mona/__init__.py
mona/app.py
mona/cli.py
mona/dag.py
mona/dirtask.py
mona/errors.py
mona/files.py
mona/futures.py
mona/hashing.py
mona/json.py
mona/pluggable.py
mona/plugins/__init__.py
mona/plugins/cache.py
mona/plugins/files.py
mona/plugins/parallel.py
mona/plugins/tmpdir.py
mona/pyhash.py
mona/remotes.py
mona/rules.py
mona/runners.py
mona/sci/__init__.py
mona/sci/aims/__init__.py
mona/sci/aims/aims.py
mona/sci/aims/aims.tx
mona/sci/aims/dsl.py
mona/sci/aims/parse.py
mona/sci/atom-data.csv
mona/sci/geomlib.py
mona/sci/tex.py
mona/sessions.py
mona/table.py
mona/tasks.py
mona/utils.py
mona-0.2.6.dist-info/entry_points.txt
mona-0.2.6.dist-info/LICENSE
mona-0.2.6.dist-info/WHEEL
mona-0.2.6.dist-info/METADATA
mona-0.2.6.dist-info/RECORD
