Metadata-Version: 2.1
Name: mona
Version: 0.2.6
Summary: Calculation framework
Home-page: https://github.com/azag0/mona
License: MPL-2.0
Author: Jan Hermann
Author-email: dev@janhermann.cz
Requires-Python: >=3.7,<4.0
Classifier: Development Status :: 3 - Alpha
Classifier: Environment :: Console
Classifier: Intended Audience :: Developers
Classifier: Intended Audience :: Science/Research
Classifier: License :: OSI Approved
Classifier: Operating System :: POSIX
Classifier: Programming Language :: Python :: 3
Classifier: Programming Language :: Python :: 3.7
Classifier: Topic :: Scientific/Engineering
Classifier: Topic :: Utilities
Provides-Extra: cov
Provides-Extra: doc
Provides-Extra: sci
Provides-Extra: test
Requires-Dist: click (>=7.0,<8.0)
Requires-Dist: coverage (>=4.5,<5.0); extra == "cov"
Requires-Dist: graphviz (>=0.10.0,<0.11.0)
Requires-Dist: jinja2 (>=2.10,<3.0); extra == "sci"
Requires-Dist: numpy (>=1.15,<2.0); extra == "sci"
Requires-Dist: pytest (>=3.8,<4.0); extra == "test"
Requires-Dist: pytest-mock (>=1.10,<2.0); extra == "test"
Requires-Dist: sphinx (>=1.8,<2.0); extra == "doc"
Requires-Dist: sphinxcontrib-asyncio (>=0.2.0,<0.3.0); extra == "doc"
Requires-Dist: textx (>=1.5,<1.6); extra == "sci"
Requires-Dist: toml (>=0.9.6,<0.10.0)
Requires-Dist: typing_extensions (>=3.6,<4.0)
Project-URL: Documentation, https://azag0.github.io/mona
Project-URL: Repository, https://github.com/azag0/mona
